wehyconfig/__init__.py
wehyconfig/wehyconfig.py
wehyconfig-0.3.2.dist-info/LICENSE
wehyconfig-0.3.2.dist-info/METADATA
wehyconfig-0.3.2.dist-info/WHEEL
wehyconfig-0.3.2.dist-info/RECORD
